anomalouslib/__init__.py
anomalouslib/constants.py
anomalouslib/analysis/DataAnalyzer.py
anomalouslib/analysis/ModelAnalyzer.py
anomalouslib/analysis/__init__.py
anomalouslib/analysis/metrics.py
anomalouslib/data/DatasetGenerator.py
anomalouslib/data/__init__.py
anomalouslib/data/postprocessing.py
anomalouslib/data/preprocessing.py
anomalouslib/models/__init__.py
anomalouslib/models/model_handler.py
anomalouslib/models/testing_utils.py
anomalouslib/models/training_utils.py
anomalouslib/results/__init__.py
anomalouslib/results/results.py
anomalouslib/utils/__init__.py
anomalouslib/utils/load_save_like.py
anomalouslib/utils/logger.py
anomalouslib-0.2.2.dist-info/licenses/LICENSE
anomalouslib-0.2.2.dist-info/METADATA
anomalouslib-0.2.2.dist-info/WHEEL
anomalouslib-0.2.2.dist-info/top_level.txt
anomalouslib-0.2.2.dist-info/RECORD
