Metadata-Version: 2.4
Name: AnomalousLib
Version: 0.2.2
Summary: AnomalousLib is a Python library designed for the study of anomalous diffusion. It enables dataset generation, statistical analysis, model inference, and integrated result visualization.
Author-email: Joan Massallé Richart <jmassalle@gmail.com>
License: MIT
Project-URL: Homepage, https://github.com/tu_usuario/mi_libreria
Requires-Python: >=3.12.10
License-File: LICENSE
Requires-Dist: numpy>=2.2.6
Requires-Dist: scipy>=1.15.3
Requires-Dist: fbm>=0.3.0
Requires-Dist: pandas>=2.2.3
Requires-Dist: scikit-learn>=1.6.1
Requires-Dist: torch>=2.7.0
Requires-Dist: dill>=0.4.0
Requires-Dist: matplotlib>=3.10.3
Dynamic: license-file
